README.rst
setup.py
wzry/__init__ - 副本.py
wzry/__init__.py
wzry.egg-info/PKG-INFO
wzry.egg-info/SOURCES.txt
wzry.egg-info/dependency_links.txt
wzry.egg-info/top_level.txt